shell_tools/__init__.py
shell_tools/cli.py
shell_tools/dirs/__init__.py
shell_tools/dirs/search.py
shell_tools/files/__init__.py
shell_tools/files/random.py
shell_tools/git/__init__.py
shell_tools/git/misc.py
shell_tools-1.2.5.dist-info/entry_points.txt
shell_tools-1.2.5.dist-info/LICENSE
shell_tools-1.2.5.dist-info/METADATA
shell_tools-1.2.5.dist-info/WHEEL
shell_tools-1.2.5.dist-info/RECORD
