Metadata-Version: 2.3
Name: shell-tools
Version: 1.2.5
Summary: Set of Python applications/scripts for different purposes
License: MIT
Author: Sergii Lovygin
Author-email: lovygin.dev@gmail.com
Requires-Python: >=3.12
Classifier: License :: OSI Approved :: MIT License
Classifier: Operating System :: OS Independent
Classifier: Programming Language :: Python :: 3
Classifier: Programming Language :: Python :: 3.12
Classifier: Programming Language :: Python :: 3.13
Requires-Dist: click (==8.1.8)
Project-URL: Homepage, https://github.com/stanykey/shell-tools
